spike2py_preprocess/__init__.py
spike2py_preprocess/__main__.py
spike2py_preprocess/study.py
spike2py_preprocess/subject.py
spike2py_preprocess/trial.py
spike2py_preprocess/trial_sections.py
spike2py_preprocess/utils.py
spike2py_preprocess-0.1.14.dist-info/LICENSE
spike2py_preprocess-0.1.14.dist-info/METADATA
spike2py_preprocess-0.1.14.dist-info/WHEEL
spike2py_preprocess-0.1.14.dist-info/top_level.txt
spike2py_preprocess-0.1.14.dist-info/RECORD
