Metadata-Version: 2.1
Name: spike2py-preprocess
Version: 0.1.14
Summary: "Preprocess data with spike2py."
Home-page: https://github.com/MartinHeroux/spike2py_preprocess
Author: Martin Heroux
Author-email: "Martin Heroux" <heroux.martin@gmail.com>
License: GPLv3
Classifier: License :: OSI Approved :: GNU General Public License v3 (GPLv3)
Classifier: Programming Language :: Python :: 3
Classifier: Programming Language :: Python :: 3.10
Classifier: Programming Language :: Python :: 3.11
Classifier: Intended Audience :: Science/Research
Requires-Python: >=3.10
License-File: LICENSE
Requires-Dist: spike2py
Requires-Dist: rich
Requires-Dist: typer
Requires-Dist: PyPDF2
